{"classname":null,"name":null,"animation":{"classname":null,"name":"AnimationManager","actionlist":[]},"dataScale":1,"designHeight":2160,"designWidth":1080,"textures":[],"texturesPng":["../lutu.png","../fh01.png","../fh02.png","../head.png","../password.png","../bkgrd.png","../750_80_09.png","../200_70_f.png","../200_70_f1.png","../200_70_m.png","../200_70_m1.png","../200_70_j.png","../200_70_j1.png","../bkgrd1920.png","../xingxiang.png","../400_90_03.png","../xk800.png","../name1.png","../750_90_09.png","../captcha.png","../anniu.png","../menwomen.png","../biaoji2.png","../biaoji1.png","../banjihao.png","../erweima.png","../shoujihao.png","../shoujihao.png"],"version":"1.6.0.0","widgetTree":{"classname":"Panel","name":null,"children":[{"classname":"ImageView","name":null,"children":[{"classname":"Button","name":null,"children":[],"options":{"__type":"ButtonSurrogate:#EditorCommon.JsonModel.Component.GUI","classname":"Button","name":"Button_back","ZOrder":0,"actiontag":21176078,"anchorPointX":0,"anchorPointY":0,"classType":"CocoStudio.EngineAdapterWrap.CSButton","colorB":255,"colorG":255,"colorR":255,"customProperty":"","flipX":false,"flipY":false,"height":130,"ignoreSize":false,"layoutParameter":null,"opacity":255,"positionPercentX":0,"positionPercentY":0,"positionType":0,"rotation":0,"scaleX":1,"scaleY":1,"sizePercentX":0.222222,"sizePercentY":1,"sizeType":0,"tag":601,"touchAble":true,"useMergedTexture":false,"visible":true,"width":240,"x":0,"y":0,"capInsetsHeight":1,"capInsetsWidth":1,"capInsetsX":0,"capInsetsY":0,"disabled":null,"disabledData":{"path":null,"plistFile":null,"resourceType":0},"fontName":"微软雅黑","fontSize":18,"fontType":0,"normal":null,"normalData":{"path":"../fh01.png","plistFile":"","resourceType":0},"pressed":null,"pressedData":{"path":"../fh02.png","plistFile":"","resourceType":0},"scale9Enable":false,"scale9Height":130,"scale9Width":240,"text":"","textColorB":255,"textColorG":255,"textColorR":255}},{"classname":"Label","name":null,"children":[],"options":{"__type":"LabelSurrogate:#EditorCommon.JsonModel.Component.GUI","classname":"Label","name":"Label_6_0","ZOrder":0,"actiontag":8132533,"anchorPointX":0.5,"anchorPointY":0.5,"classType":"CocoStudio.EngineAdapterWrap.CSLabel","colorB":255,"colorG":255,"colorR":255,"customProperty":"","flipX":false,"flipY":false,"height":65,"ignoreSize":true,"layoutParameter":null,"opacity":255,"positionPercentX":0.5,"positionPercentY":0.5,"positionType":0,"rotation":0,"scaleX":1,"scaleY":1,"sizePercentX":0.231481,"sizePercentY":0.5,"sizeType":0,"tag":27158,"touchAble":false,"useMergedTexture":false,"visible":true,"width":250,"x":540,"y":65,"areaHeight":0,"areaWidth":0,"fontFile":null,"fontName":"微软雅黑","fontSize":50,"hAlignment":1,"text":"加入新班级","touchScaleEnable":false,"vAlignment":0}}],"options":{"__type":"ImageViewSurrogate:#EditorCommon.JsonModel.Component.GUI","classname":"ImageView","name":"Image_2","ZOrder":0,"actiontag":43945239,"anchorPointX":0,"anchorPointY":0,"classType":"CocoStudio.EngineAdapterWrap.CSImageView","colorB":255,"colorG":255,"colorR":255,"customProperty":"","flipX":false,"flipY":false,"height":130,"ignoreSize":false,"layoutParameter":null,"opacity":255,"positionPercentX":0,"positionPercentY":0.939815,"positionType":0,"rotation":0,"scaleX":1,"scaleY":1,"sizePercentX":1,"sizePercentY":0.0601852,"sizeType":0,"tag":600,"touchAble":false,"useMergedTexture":false,"visible":true,"width":1080,"x":0,"y":2030,"capInsetsHeight":1,"capInsetsWidth":1,"capInsetsX":0,"capInsetsY":0,"fileName":null,"fileNameData":{"path":"../lutu.png","plistFile":"","resourceType":0},"scale9Enable":false,"scale9Height":130,"scale9Width":1080}},{"classname":"Panel","name":null,"children":[{"classname":"ImageView","name":null,"children":[{"classname":"Panel","name":null,"children":[],"options":{"__type":"PanelSurrogate:#EditorCommon.JsonModel.Component.GUI","classname":"Panel","name":"Panel_274","ZOrder":0,"actiontag":58965015,"anchorPointX":0,"anchorPointY":0,"classType":"CocoStudio.EngineAdapterWrap.CSPanel","colorB":255,"colorG":255,"colorR":255,"customProperty":"","flipX":false,"flipY":false,"height":4,"ignoreSize":false,"layoutParameter":null,"opacity":255,"positionPercentX":-0.5,"positionPercentY":-0.505618,"positionType":0,"rotation":0,"scaleX":1,"scaleY":1,"sizePercentX":1,"sizePercentY":0.00898876,"sizeType":0,"tag":40818,"touchAble":true,"useMergedTexture":false,"visible":true,"width":1080,"x":-540,"y":-225,"adaptScreen":false,"backGroundImage":null,"backGroundImageData":null,"backGroundScale9Enable":false,"bgColorB":216,"bgColorG":216,"bgColorOpacity":100,"bgColorR":216,"bgEndColorB":255,"bgEndColorG":200,"bgEndColorR":150,"bgStartColorB":255,"bgStartColorG":255,"bgStartColorR":255,"capInsetsHeight":1,"capInsetsWidth":1,"capInsetsX":0,"capInsetsY":0,"clipAble":false,"colorType":1,"layoutType":0,"vectorX":0,"vectorY":-0.5}}],"options":{"__type":"ImageViewSurrogate:#EditorCommon.JsonModel.Component.GUI","classname":"ImageView","name":"Image_27","ZOrder":0,"actiontag":14654394,"anchorPointX":0.5,"anchorPointY":0.5,"classType":"CocoStudio.EngineAdapterWrap.CSImageView","colorB":255,"colorG":255,"colorR":255,"customProperty":"","flipX":false,"flipY":false,"height":445,"ignoreSize":false,"layoutParameter":null,"opacity":255,"positionPercentX":0.5,"positionPercentY":0.505618,"positionType":0,"rotation":0,"scaleX":1,"scaleY":1,"sizePercentX":1,"sizePercentY":1,"sizeType":0,"tag":40203,"touchAble":false,"useMergedTexture":false,"visible":true,"width":1080,"x":540,"y":225,"capInsetsHeight":1,"capInsetsWidth":1,"capInsetsX":0,"capInsetsY":0,"fileName":null,"fileNameData":{"path":"../lutu.png","plistFile":"","resourceType":0},"scale9Enable":false,"scale9Height":445,"scale9Width":1080}},{"classname":"Panel","name":null,"children":[{"classname":"Label","name":null,"children":[],"options":{"__type":"LabelSurrogate:#EditorCommon.JsonModel.Component.GUI","classname":"Label","name":"_UserNickName","ZOrder":0,"actiontag":2583167,"anchorPointX":0.5,"anchorPointY":0.5,"classType":"CocoStudio.EngineAdapterWrap.CSLabel","colorB":255,"colorG":255,"colorR":255,"customProperty":"","flipX":false,"flipY":false,"height":52,"ignoreSize":false,"layoutParameter":null,"opacity":255,"positionPercentX":0.5,"positionPercentY":-0.416667,"positionType":0,"rotation":0,"scaleX":1,"scaleY":1,"sizePercentX":5.12821,"sizePercentY":0.333333,"sizeType":0,"tag":40615,"touchAble":false,"useMergedTexture":false,"visible":true,"width":800,"x":78,"y":-65,"areaHeight":52,"areaWidth":800,"fontFile":null,"fontName":"微软雅黑","fontSize":40,"hAlignment":1,"text":"李小璐","touchScaleEnable":false,"vAlignment":0}},{"classname":"ImageView","name":null,"children":[],"options":{"__type":"ImageViewSurrogate:#EditorCommon.JsonModel.Component.GUI","classname":"ImageView","name":"_userImage","ZOrder":0,"actiontag":65867000,"anchorPointX":0.5,"anchorPointY":0.5,"classType":"CocoStudio.EngineAdapterWrap.CSImageView","colorB":255,"colorG":255,"colorR":255,"customProperty":"","flipX":false,"flipY":false,"height":150,"ignoreSize":false,"layoutParameter":null,"opacity":255,"positionPercentX":0.5,"positionPercentY":0.49359,"positionType":0,"rotation":0,"scaleX":1,"scaleY":1,"sizePercentX":0.961538,"sizePercentY":0.961538,"sizeType":0,"tag":40617,"touchAble":false,"useMergedTexture":false,"visible":true,"width":150,"x":78,"y":77,"capInsetsHeight":1,"capInsetsWidth":1,"capInsetsX":0,"capInsetsY":0,"fileName":null,"fileNameData":{"path":"../head.png","plistFile":"","resourceType":0},"scale9Enable":false,"scale9Height":150,"scale9Width":150}}],"options":{"__type":"PanelSurrogate:#EditorCommon.JsonModel.Component.GUI","classname":"Panel","name":"Panel_44","ZOrder":0,"actiontag":28918215,"anchorPointX":0,"anchorPointY":0,"classType":"CocoStudio.EngineAdapterWrap.CSPanel","colorB":255,"colorG":255,"colorR":255,"customProperty":"","flipX":false,"flipY":false,"height":156,"ignoreSize":false,"layoutParameter":null,"opacity":255,"positionPercentX":0.426852,"positionPercentY":0.442697,"positionType":0,"rotation":0,"scaleX":1,"scaleY":1,"sizePercentX":0.144444,"sizePercentY":0.350562,"sizeType":0,"tag":40614,"touchAble":true,"useMergedTexture":false,"visible":true,"width":156,"x":461,"y":197,"adaptScreen":false,"backGroundImage":null,"backGroundImageData":null,"backGroundScale9Enable":false,"bgColorB":255,"bgColorG":255,"bgColorOpacity":0,"bgColorR":255,"bgEndColorB":255,"bgEndColorG":200,"bgEndColorR":150,"bgStartColorB":255,"bgStartColorG":255,"bgStartColorR":255,"capInsetsHeight":1,"capInsetsWidth":1,"capInsetsX":0,"capInsetsY":0,"clipAble":false,"colorType":1,"layoutType":0,"vectorX":0,"vectorY":-0.5}}],"options":{"__type":"PanelSurrogate:#EditorCommon.JsonModel.Component.GUI","classname":"Panel","name":"Panel_26","ZOrder":0,"actiontag":16950076,"anchorPointX":0,"anchorPointY":0,"classType":"CocoStudio.EngineAdapterWrap.CSPanel","colorB":255,"colorG":255,"colorR":255,"customProperty":"","flipX":false,"flipY":false,"height":445,"ignoreSize":false,"layoutParameter":null,"opacity":255,"positionPercentX":0,"positionPercentY":0.73287,"positionType":0,"rotation":0,"scaleX":1,"scaleY":1,"sizePercentX":1,"sizePercentY":0.206019,"sizeType":0,"tag":40202,"touchAble":true,"useMergedTexture":false,"visible":true,"width":1080,"x":0,"y":1583,"adaptScreen":false,"backGroundImage":null,"backGroundImageData":null,"backGroundScale9Enable":false,"bgColorB":255,"bgColorG":255,"bgColorOpacity":255,"bgColorR":255,"bgEndColorB":255,"bgEndColorG":200,"bgEndColorR":150,"bgStartColorB":255,"bgStartColorG":255,"bgStartColorR":255,"capInsetsHeight":1,"capInsetsWidth":1,"capInsetsX":0,"capInsetsY":0,"clipAble":false,"colorType":1,"layoutType":0,"vectorX":0,"vectorY":-0.5}},{"classname":"Panel","name":null,"children":[{"classname":"Label","name":null,"children":[],"options":{"__type":"LabelSurrogate:#EditorCommon.JsonModel.Component.GUI","classname":"Label","name":"Label_2","ZOrder":0,"actiontag":62567701,"anchorPointX":0.5,"anchorPointY":0.5,"classType":"CocoStudio.EngineAdapterWrap.CSLabel","colorB":68,"colorG":68,"colorR":68,"customProperty":"","flipX":false,"flipY":false,"height":52,"ignoreSize":false,"layoutParameter":null,"opacity":255,"positionPercentX":0.498148,"positionPercentY":0.935917,"positionType":0,"rotation":0,"scaleX":1,"scaleY":1,"sizePercentX":0.740741,"sizePercentY":0.0387481,"sizeType":0,"tag":40479,"touchAble":false,"useMergedTexture":false,"visible":true,"width":800,"x":538,"y":1256,"areaHeight":52,"areaWidth":800,"fontFile":null,"fontName":"微软雅黑","fontSize":40,"hAlignment":1,"text":"请选择你要加入班级的方式","touchScaleEnable":false,"vAlignment":0}},{"classname":"Button","name":null,"children":[{"classname":"ImageView","name":null,"children":[],"options":{"__type":"ImageViewSurrogate:#EditorCommon.JsonModel.Component.GUI","classname":"ImageView","name":"Image_259","ZOrder":0,"actiontag":35612247,"anchorPointX":0.5,"anchorPointY":0.5,"classType":"CocoStudio.EngineAdapterWrap.CSImageView","colorB":255,"colorG":255,"colorR":255,"customProperty":"","flipX":false,"flipY":false,"height":94,"ignoreSize":false,"layoutParameter":null,"opacity":255,"positionPercentX":0,"positionPercentY":0,"positionType":0,"rotation":0,"scaleX":1,"scaleY":1,"sizePercentX":0.522222,"sizePercentY":0.522222,"sizeType":0,"tag":40803,"touchAble":false,"useMergedTexture":false,"visible":true,"width":94,"x":0,"y":0,"capInsetsHeight":1,"capInsetsWidth":1,"capInsetsX":0,"capInsetsY":0,"fileName":null,"fileNameData":{"path":"../banjihao.png","plistFile":"","resourceType":0},"scale9Enable":false,"scale9Height":94,"scale9Width":94}},{"classname":"Label","name":null,"children":[],"options":{"__type":"LabelSurrogate:#EditorCommon.JsonModel.Component.GUI","classname":"Label","name":"Label_260","ZOrder":0,"actiontag":10458840,"anchorPointX":0.5,"anchorPointY":0.5,"classType":"CocoStudio.EngineAdapterWrap.CSLabel","colorB":68,"colorG":68,"colorR":68,"customProperty":"","flipX":false,"flipY":false,"height":50,"ignoreSize":false,"layoutParameter":null,"opacity":255,"positionPercentX":0,"positionPercentY":-0.511111,"positionType":0,"rotation":0,"scaleX":1,"scaleY":1,"sizePercentX":1.66667,"sizePercentY":0.277778,"sizeType":0,"tag":40804,"touchAble":false,"useMergedTexture":false,"visible":true,"width":300,"x":0,"y":-92,"areaHeight":50,"areaWidth":300,"fontFile":null,"fontName":"微软雅黑","fontSize":40,"hAlignment":1,"text":"输入班级号","touchScaleEnable":false,"vAlignment":0}}],"options":{"__type":"ButtonSurrogate:#EditorCommon.JsonModel.Component.GUI","classname":"Button","name":"Button_258","ZOrder":0,"actiontag":61047994,"anchorPointX":0.5,"anchorPointY":0.5,"classType":"CocoStudio.EngineAdapterWrap.CSButton","colorB":255,"colorG":255,"colorR":255,"customProperty":"","flipX":false,"flipY":false,"height":180,"ignoreSize":false,"layoutParameter":null,"opacity":255,"positionPercentX":0.15,"positionPercentY":0.817437,"positionType":0,"rotation":0,"scaleX":1,"scaleY":1,"sizePercentX":0.166667,"sizePercentY":0.134128,"sizeType":0,"tag":40802,"touchAble":true,"useMergedTexture":false,"visible":true,"width":180,"x":162,"y":1097,"capInsetsHeight":1,"capInsetsWidth":1,"capInsetsX":0,"capInsetsY":0,"disabled":null,"disabledData":{"path":null,"plistFile":null,"resourceType":0},"fontName":"微软雅黑","fontSize":14,"fontType":0,"normal":null,"normalData":{"path":"../anniu.png","plistFile":"","resourceType":0},"pressed":null,"pressedData":{"path":"../anniu.png","plistFile":"","resourceType":0},"scale9Enable":false,"scale9Height":180,"scale9Width":180,"text":"","textColorB":255,"textColorG":255,"textColorR":255}},{"classname":"Button","name":null,"children":[{"classname":"ImageView","name":null,"children":[],"options":{"__type":"ImageViewSurrogate:#EditorCommon.JsonModel.Component.GUI","classname":"ImageView","name":"Image_259","ZOrder":0,"actiontag":43178598,"anchorPointX":0.5,"anchorPointY":0.5,"classType":"CocoStudio.EngineAdapterWrap.CSImageView","colorB":255,"colorG":255,"colorR":255,"customProperty":"","flipX":false,"flipY":false,"height":94,"ignoreSize":false,"layoutParameter":null,"opacity":255,"positionPercentX":0,"positionPercentY":0,"positionType":0,"rotation":0,"scaleX":1,"scaleY":1,"sizePercentX":0.522222,"sizePercentY":0.522222,"sizeType":0,"tag":40809,"touchAble":false,"useMergedTexture":false,"visible":true,"width":94,"x":0,"y":0,"capInsetsHeight":1,"capInsetsWidth":1,"capInsetsX":0,"capInsetsY":0,"fileName":null,"fileNameData":{"path":"../erweima.png","plistFile":"","resourceType":0},"scale9Enable":false,"scale9Height":94,"scale9Width":94}},{"classname":"Label","name":null,"children":[],"options":{"__type":"LabelSurrogate:#EditorCommon.JsonModel.Component.GUI","classname":"Label","name":"Label_260","ZOrder":0,"actiontag":53063069,"anchorPointX":0.5,"anchorPointY":0.5,"classType":"CocoStudio.EngineAdapterWrap.CSLabel","colorB":68,"colorG":68,"colorR":68,"customProperty":"","flipX":false,"flipY":false,"height":50,"ignoreSize":false,"layoutParameter":null,"opacity":255,"positionPercentX":0,"positionPercentY":-0.511111,"positionType":0,"rotation":0,"scaleX":1,"scaleY":1,"sizePercentX":1.66667,"sizePercentY":0.277778,"sizeType":0,"tag":40810,"touchAble":false,"useMergedTexture":false,"visible":true,"width":300,"x":0,"y":-92,"areaHeight":50,"areaWidth":300,"fontFile":null,"fontName":"微软雅黑","fontSize":40,"hAlignment":1,"text":"扫一扫二维码","touchScaleEnable":false,"vAlignment":0}}],"options":{"__type":"ButtonSurrogate:#EditorCommon.JsonModel.Component.GUI","classname":"Button","name":"Button_259","ZOrder":0,"actiontag":30122741,"anchorPointX":0.5,"anchorPointY":0.5,"classType":"CocoStudio.EngineAdapterWrap.CSButton","colorB":255,"colorG":255,"colorR":255,"customProperty":"","flipX":false,"flipY":false,"height":180,"ignoreSize":false,"layoutParameter":null,"opacity":255,"positionPercentX":0.499074,"positionPercentY":0.817437,"positionType":0,"rotation":0,"scaleX":1,"scaleY":1,"sizePercentX":0.166667,"sizePercentY":0.134128,"sizeType":0,"tag":40808,"touchAble":true,"useMergedTexture":false,"visible":true,"width":180,"x":539,"y":1097,"capInsetsHeight":1,"capInsetsWidth":1,"capInsetsX":0,"capInsetsY":0,"disabled":null,"disabledData":{"path":null,"plistFile":null,"resourceType":0},"fontName":"微软雅黑","fontSize":14,"fontType":0,"normal":null,"normalData":{"path":"../anniu.png","plistFile":"","resourceType":0},"pressed":null,"pressedData":{"path":"../anniu.png","plistFile":"","resourceType":0},"scale9Enable":false,"scale9Height":180,"scale9Width":180,"text":"","textColorB":255,"textColorG":255,"textColorR":255}},{"classname":"Button","name":null,"children":[{"classname":"ImageView","name":null,"children":[],"options":{"__type":"ImageViewSurrogate:#EditorCommon.JsonModel.Component.GUI","classname":"ImageView","name":"Image_259","ZOrder":0,"actiontag":50544678,"anchorPointX":0.5,"anchorPointY":0.5,"classType":"CocoStudio.EngineAdapterWrap.CSImageView","colorB":255,"colorG":255,"colorR":255,"customProperty":"","flipX":false,"flipY":false,"height":94,"ignoreSize":false,"layoutParameter":null,"opacity":255,"positionPercentX":0,"positionPercentY":0,"positionType":0,"rotation":0,"scaleX":1,"scaleY":1,"sizePercentX":0.522222,"sizePercentY":0.522222,"sizeType":0,"tag":40815,"touchAble":false,"useMergedTexture":false,"visible":true,"width":94,"x":0,"y":0,"capInsetsHeight":1,"capInsetsWidth":1,"capInsetsX":0,"capInsetsY":0,"fileName":null,"fileNameData":{"path":"../shoujihao.png","plistFile":"","resourceType":0},"scale9Enable":false,"scale9Height":94,"scale9Width":94}},{"classname":"Label","name":null,"children":[],"options":{"__type":"LabelSurrogate:#EditorCommon.JsonModel.Component.GUI","classname":"Label","name":"Label_260","ZOrder":0,"actiontag":52248921,"anchorPointX":0.5,"anchorPointY":0.5,"classType":"CocoStudio.EngineAdapterWrap.CSLabel","colorB":68,"colorG":68,"colorR":68,"customProperty":"","flipX":false,"flipY":false,"height":50,"ignoreSize":false,"layoutParameter":null,"opacity":255,"positionPercentX":0,"positionPercentY":-0.511111,"positionType":0,"rotation":0,"scaleX":1,"scaleY":1,"sizePercentX":1.66667,"sizePercentY":0.277778,"sizeType":0,"tag":40816,"touchAble":false,"useMergedTexture":false,"visible":true,"width":300,"x":0,"y":-92,"areaHeight":50,"areaWidth":300,"fontFile":null,"fontName":"微软雅黑","fontSize":40,"hAlignment":1,"text":"输入班主任","touchScaleEnable":false,"vAlignment":0}},{"classname":"Label","name":null,"children":[],"options":{"__type":"LabelSurrogate:#EditorCommon.JsonModel.Component.GUI","classname":"Label","name":"Label_273","ZOrder":0,"actiontag":60488394,"anchorPointX":0.5,"anchorPointY":0.5,"classType":"CocoStudio.EngineAdapterWrap.CSLabel","colorB":68,"colorG":68,"colorR":68,"customProperty":"","flipX":false,"flipY":false,"height":50,"ignoreSize":false,"layoutParameter":null,"opacity":255,"positionPercentX":0,"positionPercentY":-0.855556,"positionType":0,"rotation":0,"scaleX":1,"scaleY":1,"sizePercentX":0.833333,"sizePercentY":0.277778,"sizeType":0,"tag":40817,"touchAble":false,"useMergedTexture":false,"visible":true,"width":150,"x":0,"y":-154,"areaHeight":50,"areaWidth":150,"fontFile":null,"fontName":"微软雅黑","fontSize":40,"hAlignment":1,"text":"手机号","touchScaleEnable":false,"vAlignment":0}}],"options":{"__type":"ButtonSurrogate:#EditorCommon.JsonModel.Component.GUI","classname":"Button","name":"Button_260","ZOrder":0,"actiontag":10784038,"anchorPointX":0.5,"anchorPointY":0.5,"classType":"CocoStudio.EngineAdapterWrap.CSButton","colorB":255,"colorG":255,"colorR":255,"customProperty":"","flipX":false,"flipY":false,"height":180,"ignoreSize":false,"layoutParameter":null,"opacity":255,"positionPercentX":0.848148,"positionPercentY":0.817437,"positionType":0,"rotation":0,"scaleX":1,"scaleY":1,"sizePercentX":0.166667,"sizePercentY":0.134128,"sizeType":0,"tag":40814,"touchAble":true,"useMergedTexture":false,"visible":true,"width":180,"x":916,"y":1097,"capInsetsHeight":1,"capInsetsWidth":1,"capInsetsX":0,"capInsetsY":0,"disabled":null,"disabledData":{"path":null,"plistFile":null,"resourceType":0},"fontName":"微软雅黑","fontSize":14,"fontType":0,"normal":null,"normalData":{"path":"../anniu.png","plistFile":"","resourceType":0},"pressed":null,"pressedData":{"path":"../anniu.png","plistFile":"","resourceType":0},"scale9Enable":false,"scale9Height":180,"scale9Width":180,"text":"","textColorB":255,"textColorG":255,"textColorR":255}}],"options":{"__type":"PanelSurrogate:#EditorCommon.JsonModel.Component.GUI","classname":"Panel","name":"Panel_1","ZOrder":0,"actiontag":14527871,"anchorPointX":0,"anchorPointY":0,"classType":"CocoStudio.EngineAdapterWrap.CSPanel","colorB":255,"colorG":255,"colorR":255,"customProperty":"","flipX":false,"flipY":false,"height":1342,"ignoreSize":false,"layoutParameter":null,"opacity":255,"positionPercentX":0.000925926,"positionPercentY":0.111111,"positionType":0,"rotation":0,"scaleX":1,"scaleY":1,"sizePercentX":1,"sizePercentY":0.621296,"sizeType":0,"tag":40478,"touchAble":true,"useMergedTexture":false,"visible":true,"width":1080,"x":1,"y":240,"adaptScreen":false,"backGroundImage":null,"backGroundImageData":null,"backGroundScale9Enable":false,"bgColorB":255,"bgColorG":255,"bgColorOpacity":255,"bgColorR":255,"bgEndColorB":255,"bgEndColorG":200,"bgEndColorR":150,"bgStartColorB":255,"bgStartColorG":255,"bgStartColorR":255,"capInsetsHeight":1,"capInsetsWidth":1,"capInsetsX":0,"capInsetsY":0,"clipAble":false,"colorType":1,"layoutType":0,"vectorX":0,"vectorY":-0.5}}],"options":{"__type":"PanelSurrogate:#EditorCommon.JsonModel.Component.GUI","classname":"Panel","name":"Panel_26","ZOrder":0,"actiontag":-1,"anchorPointX":0,"anchorPointY":0,"classType":"CocoStudio.EngineAdapterWrap.CSPanel","colorB":255,"colorG":255,"colorR":255,"customProperty":"","flipX":false,"flipY":false,"height":2160,"ignoreSize":false,"layoutParameter":null,"opacity":255,"positionPercentX":0,"positionPercentY":0,"positionType":0,"rotation":0,"scaleX":1,"scaleY":1,"sizePercentX":1,"sizePercentY":1,"sizeType":0,"tag":3,"touchAble":true,"useMergedTexture":false,"visible":true,"width":1080,"x":0,"y":0,"adaptScreen":false,"backGroundImage":null,"backGroundImageData":null,"backGroundScale9Enable":false,"bgColorB":255,"bgColorG":255,"bgColorOpacity":255,"bgColorR":255,"bgEndColorB":255,"bgEndColorG":200,"bgEndColorR":150,"bgStartColorB":255,"bgStartColorG":255,"bgStartColorR":255,"capInsetsHeight":1,"capInsetsWidth":1,"capInsetsX":0,"capInsetsY":0,"clipAble":false,"colorType":1,"layoutType":0,"vectorX":0,"vectorY":-0.5}}}